raccoon/__init__.py
raccoon/util.py
raccoon/wiggle_cleaner.py
space_raccoon-1.0.0.dist-info/licenses/AUTHORS.rst
space_raccoon-1.0.0.dist-info/licenses/LICENSE
space_raccoon-1.0.0.dist-info/METADATA
space_raccoon-1.0.0.dist-info/WHEEL
space_raccoon-1.0.0.dist-info/top_level.txt
space_raccoon-1.0.0.dist-info/RECORD
