Metadata-Version: 2.4
Name: space-raccoon
Version: 1.0.0
Summary: Raccoon cleans modulation created by undersampling the PSF in the JWST/NIRSpec spectra.
Home-page: https://github.com/ajshajib/raccoon
Author: Anowar Shajib
Author-email: "Anowar J. Shajib" <ajshajib@gmail.com>
License-Expression: BSD-3-Clause
Project-URL: Homepage, https://github.com/ajshajib/dolphin
Keywords: dolphin,lenstronomy
Classifier: Development Status :: 5 - Production/Stable
Classifier: Intended Audience :: Science/Research
Classifier: Natural Language :: English
Classifier: Programming Language :: Python :: 3.10
Classifier: Programming Language :: Python :: 3.11
Classifier: Programming Language :: Python :: 3.12
Requires-Python: >=3.10
License-File: LICENSE
License-File: AUTHORS.rst
Dynamic: author
Dynamic: home-page
Dynamic: license-file
